SocketSwap/__init__.py
SocketSwap/context_manager.py
SocketSwap/proxy.py
SocketSwap/test_multiprocessing.py
SocketSwap/test_thread_timeout.py
SocketSwap-0.1.11.dist-info/LICENSE
SocketSwap-0.1.11.dist-info/METADATA
SocketSwap-0.1.11.dist-info/WHEEL
SocketSwap-0.1.11.dist-info/top_level.txt
SocketSwap-0.1.11.dist-info/RECORD
