Metadata-Version: 2.1
Name: SocketSwap
Version: 0.1.11
Summary: SocketSwap is a python package that allows to proxy any third-party libraries traffic through a local TCP Proxy
Home-page: https://github.com/fyx99/SocketSwap
Author: fxy99
Author-email: 
License: MIT
Classifier: Development Status :: 5 - Production/Stable
Classifier: Intended Audience :: Developers
Classifier: License :: OSI Approved :: MIT License
Classifier: Operating System :: POSIX :: Linux
Classifier: Programming Language :: Python :: 3 :: Only
Classifier: Programming Language :: Python :: 3
Classifier: Programming Language :: Python :: 3.4
Classifier: Programming Language :: Python :: 3.5
License-File: LICENSE
